[{"skillLevel":"7","skillName":"Arrow Rain"},{"skillLevel":"8","skillName":"Quick Shot"},{"skillLevel":"7","skillName":"Painstrike Gale"},{"skillLevel":"7","skillName":"Illusion Arrow"},{"skillLevel":"9","skillName":"Burst Shell"},{"skillLevel":"8","skillName":"Flash Arrow"},{"skillLevel":"8","skillName":"Heavenly Bow"},{"skillLevel":"8","skillName":"Mind's Eye"},{"skillLevel":"7","skillName":"Ice Cage"},{"skillLevel":"9","skillName":"Obliterate Shell"},{"skillLevel":"8","skillName":"Venom Mist Shell"},{"skillLevel":"7","skillName":"Seeking Bolt"},{"skillLevel":"8","skillName":"Cloaking"}]